openid_connect_op/__init__.py
openid_connect_op/admin.py
openid_connect_op/apps.py
openid_connect_op/decorators.py
openid_connect_op/models.py
openid_connect_op/signals.py
openid_connect_op/translation.py
openid_connect_op/urls.py
openid_connect_op/userinfo_providers.py
openid_connect_op/locale/cs/LC_MESSAGES/django.po
openid_connect_op/locale/en/LC_MESSAGES/django.po
openid_connect_op/management/__init__.py
openid_connect_op/management/commands/__init__.py
openid_connect_op/management/commands/create_jwt_keys.py
openid_connect_op/management/commands/register_openid_client.py
openid_connect_op/migrations/0001_initial.py
openid_connect_op/migrations/0002_openidclient_userinfo_in_id_token.py
openid_connect_op/migrations/__init__.py
openid_connect_op/templates/django-open-id/consent-form.html
openid_connect_op/templates/django-open-id/consent.html
openid_connect_op/templates/django-open-id/form_post_response_mode.html
openid_connect_op/utils/__init__.py
openid_connect_op/utils/crypto.py
openid_connect_op/utils/jwt.py
openid_connect_op/utils/params.py
openid_connect_op/utils/secrets_backport.py
openid_connect_op/views/__init__.py
openid_connect_op/views/authentication_request_view.py
openid_connect_op/views/client_configuration_view.py
openid_connect_op/views/consent_view.py
openid_connect_op/views/dynamic_registration_view.py
openid_connect_op/views/errors.py
openid_connect_op/views/jwks_view.py
openid_connect_op/views/logout_request_view.py
openid_connect_op/views/parameters.py
openid_connect_op/views/token_request_view.py
openid_connect_op/views/userinfo_request_view.py
openid_connect_op/views/wellknown.py
tests/__init__.py
tests/backends.py
tests/middleware.py
tests/run_sample_server.py
tests/setup_sample_server.py
tests/test_settings.py
tests/urls.py
tests/views.py
tests/client/__init__.py
tests/crypto/__init__.py
tests/crypto/test_crypto.py
tests/management/__init__.py
tests/management/commands/__init__.py
tests/openid_op_tests/__init__.py
django_openid_op-0.5.0.dist-info/LICENSE
django_openid_op-0.5.0.dist-info/METADATA
django_openid_op-0.5.0.dist-info/WHEEL
django_openid_op-0.5.0.dist-info/top_level.txt
django_openid_op-0.5.0.dist-info/RECORD
